bannock/__init__.py
bannock/maze.py
bannock/model.py
bannock/numerics.c
bannock/numerics.pyx
bannock/numerics.so
bannock/secretion.py
bannock/walls.py
bannock/plot/__init__.py
bannock/plot/chemical_distribution.py
bannock/plot/plot.py
bannock/utils/__init__.py
bannock/utils/run_utils.py
bannock/utils/scripts.py
bannock/utils/utils.py
bannock-0.5.0.dist-info/DESCRIPTION.rst
bannock-0.5.0.dist-info/entry_points.txt
bannock-0.5.0.dist-info/METADATA
bannock-0.5.0.dist-info/metadata.json
bannock-0.5.0.dist-info/pbr.json
bannock-0.5.0.dist-info/RECORD
bannock-0.5.0.dist-info/top_level.txt
bannock-0.5.0.dist-info/WHEEL
