Metadata-Version: 2.0
Name: bannock
Version: 0.5.0
Summary: Agent-based simulations in confined environments
Home-page: https://github.com/eddiejessup/bannock
Author: Elliot Marsden
Author-email: elliot.marsden@gmail.com
License: BSD
Keywords: bannock
Platform: UNKNOWN
Classifier: Development Status :: 4 - Beta
Classifier: Intended Audience :: Science/Research
Classifier: Topic :: Scientific/Engineering
Classifier: License :: OSI Approved :: BSD License
Classifier: Natural Language :: English
Classifier: Programming Language :: Python :: 2
Classifier: Programming Language :: Python :: 2.6
Classifier: Programming Language :: Python :: 2.7
Classifier: Programming Language :: Python :: 3
Classifier: Programming Language :: Python :: 3.3
Classifier: Programming Language :: Python :: 3.4
Requires-Dist: Cython
Requires-Dist: numpy
Requires-Dist: matplotlib
Requires-Dist: ciabatta
Requires-Dist: agaro
Requires-Dist: spatious
Requires-Dist: cellulist
Requires-Dist: fealty
Requires-Dist: clustrous
